README.md
setup.py
ifaceinfo/__init__.py
ifaceinfo/ifaceinfo.py
ifaceinfo/ifaceinfotools.py
ifaceinfo/ifaceroutes.py
ifaceinfo/ifaceversion.py
ifaceinfo/tcpconn.py
ifaceinfo/udpconn.py
ifaceinfo.egg-info/PKG-INFO
ifaceinfo.egg-info/SOURCES.txt
ifaceinfo.egg-info/dependency_links.txt
ifaceinfo.egg-info/top_level.txt